gncpy-2.0.3.dist-info/METADATA
gncpy-2.0.3.dist-info/RECORD
gncpy-2.0.3.dist-info/WHEEL
gncpy-2.0.3.dist-info/licenses/LICENSE
include/gncpy/Exceptions.h
include/gncpy/SerializeMacros.h
include/gncpy/core.h
include/gncpy/Utilities.h
include/gncpy/filters/IBayesFilter.h
include/gncpy/filters/Kalman.h
include/gncpy/filters/ExtendedKalman.h
include/gncpy/filters/Parameters.h
include/gncpy/dynamics/Exceptions.h
include/gncpy/dynamics/ClohessyWiltshire2D.h
include/gncpy/dynamics/ILinearDynamics.h
include/gncpy/dynamics/IDynamics.h
include/gncpy/dynamics/ClohessyWiltshire.h
include/gncpy/dynamics/DoubleIntegrator.h
include/gncpy/dynamics/INonLinearDynamics.h
include/gncpy/dynamics/CurvilinearMotion.h
include/gncpy/dynamics/Parameters.h
include/gncpy/math/Exceptions.h
include/gncpy/math/SerializeEigen.h
include/gncpy/math/Math.h
include/gncpy/measurements/Exceptions.h
include/gncpy/measurements/RangeAndBearing.h
include/gncpy/measurements/StateObservation.h
include/gncpy/measurements/INonLinearMeasModel.h
include/gncpy/measurements/ILinearMeasModel.h
include/gncpy/measurements/Parameters.h
include/gncpy/measurements/IMeasModel.h
include/gncpy/control/Exceptions.h
include/gncpy/control/IControlModel.h
include/gncpy/control/ILinearControlModel.h
include/gncpy/control/StateControl.h
include/gncpy/control/Parameters.h
include/eigen3/signature_of_eigen3_matrix_library
include/eigen3/unsupported/Eigen/AlignedVector3
include/eigen3/unsupported/Eigen/EulerAngles
include/eigen3/unsupported/Eigen/MPRealSupport
include/eigen3/unsupported/Eigen/Splines
include/eigen3/unsupported/Eigen/Skyline
include/eigen3/unsupported/Eigen/SpecialFunctions
include/eigen3/unsupported/Eigen/IterativeSolvers
include/eigen3/unsupported/Eigen/LevenbergMarquardt
include/eigen3/unsupported/Eigen/AutoDiff
include/eigen3/unsupported/Eigen/AdolcForward
include/eigen3/unsupported/Eigen/BVH
include/eigen3/unsupported/Eigen/FFT
include/eigen3/unsupported/Eigen/MoreVectorization
include/eigen3/unsupported/Eigen/MatrixFunctions
include/eigen3/unsupported/Eigen/Polynomials
