Metadata-Version: 2.1
Name: gncpy
Version: 2.0.3
Summary: A package for Guidance, Navigation, and Control (GNC) algorithms.
Keywords: Guidance Navigation and Control,dynamics,kalman filter,reinforcement learning
Home-page: http://lager.ua.edu/
Author: Laboratory for Autonomy GNC and Estimation Research (LAGER)
License: MIT License
Classifier: Intended Audience :: Developers
Classifier: Intended Audience :: Education
Classifier: Intended Audience :: Science/Research
Classifier: Programming Language :: Python
Classifier: Programming Language :: Python :: 3.7
Classifier: Programming Language :: Python :: 3.8
Classifier: Programming Language :: Python :: 3.9
Classifier: Topic :: Scientific/Engineering
Classifier: Topic :: Scientific/Engineering :: Artificial Intelligence
Classifier: Operating System :: POSIX :: Linux
Classifier: Operating System :: MacOS
Project-URL: Homepage, http://lager.ua.edu/
Project-URL: Documentation, https://drjdlarson.github.io/gncpy/
Project-URL: Repository, https://github.com/drjdlarson/gncpy
Requires-Python: <3.10,>=3.7
Requires-Dist: serums
Requires-Dist: numpy
Requires-Dist: scipy
Requires-Dist: matplotlib
Requires-Dist: ruamel.yaml>=0.17.21
Requires-Dist: pygame>=2.1.2; extra == "games"
Requires-Dist: gym==0.25; extra == "reinforcement-learning"
Requires-Dist: opencv-python; extra == "reinforcement-learning"
Requires-Dist: gym==0.25; extra == "all"
Requires-Dist: opencv-python; extra == "all"
Requires-Dist: pygame>=2.1.2; extra == "all"
Provides-Extra: games
Provides-Extra: reinforcement-learning
Provides-Extra: all
